<?xml version="1.0" encoding="utf-8"?>
<!DOCTYPE score-partwise  PUBLIC "-//Recordare//DTD MusicXML 3.1 Partwise//EN" "http://www.musicxml.org/dtds/partwise.dtd">
<score-partwise version="3.1">
  <movement-title>Music21 Fragment</movement-title>
  <identification>
    <creator type="composer">Music21</creator>
    <encoding>
      <encoding-date>2025-04-07</encoding-date>
      <software>music21 v.8.3.0</software>
    </encoding>
  </identification>
  <defaults>
    <scaling>
      <millimeters>7</millimeters>
      <tenths>40</tenths>
    </scaling>
  </defaults>
  <part-list>
    <score-part id="P96e94eb05f6dbb854366bd24c8c7d211">
      <part-name />
    </score-part>
  </part-list>
  <!--=========================== Part 1 ===========================-->
  <part id="P96e94eb05f6dbb854366bd24c8c7d211">
    <!--======================== Measure 150 =========================-->
    <measure number="150">
      <attributes>
        <divisions>10080</divisions>
        <key>
          <fifths>1</fifths>
        </key>
        <time>
          <beats>2</beats>
          <beat-type>4</beat-type>
        </time>
      </attributes>
      <note default-x="14.36" default-y="0">
        <pitch>
          <step>F</step>
          <alter>0</alter>
          <octave>5</octave>
        </pitch>
        <duration>2520</duration>
        <type>16th</type>
        <accidental>natural</accidental>
        <stem>down</stem>
        <beam number="1">begin</beam>
        <beam number="2">begin</beam>
      </note>
      <note default-x="42.38" default-y="-5">
        <pitch>
          <step>E</step>
          <octave>5</octave>
        </pitch>
        <duration>2520</duration>
        <type>16th</type>
        <stem>down</stem>
        <beam number="1">continue</beam>
        <beam number="2">continue</beam>
      </note>
      <note default-x="70.41" default-y="0">
        <pitch>
          <step>F</step>
          <octave>5</octave>
        </pitch>
        <duration>2520</duration>
        <type>16th</type>
        <stem>down</stem>
        <beam number="1">continue</beam>
        <beam number="2">continue</beam>
      </note>
      <note default-x="101.49" default-y="-15">
        <pitch>
          <step>C</step>
          <alter>1</alter>
          <octave>5</octave>
        </pitch>
        <duration>2520</duration>
        <type>16th</type>
        <accidental>sharp</accidental>
        <stem>down</stem>
        <beam number="1">end</beam>
        <beam number="2">end</beam>
      </note>
      <note default-x="129.51" default-y="-5">
        <pitch>
          <step>E</step>
          <octave>5</octave>
        </pitch>
        <duration>2520</duration>
        <type>16th</type>
        <stem>down</stem>
        <beam number="1">begin</beam>
        <beam number="2">begin</beam>
      </note>
      <note default-x="157.54" default-y="-10">
        <pitch>
          <step>D</step>
          <octave>5</octave>
        </pitch>
        <duration>2520</duration>
        <type>16th</type>
        <stem>down</stem>
        <beam number="1">continue</beam>
        <beam number="2">continue</beam>
      </note>
      <note default-x="185.56" default-y="-15">
        <pitch>
          <step>C</step>
          <alter>0</alter>
          <octave>5</octave>
        </pitch>
        <duration>2520</duration>
        <type>16th</type>
        <accidental>natural</accidental>
        <stem>down</stem>
        <beam number="1">continue</beam>
        <beam number="2">continue</beam>
      </note>
      <note default-x="214.5" default-y="-20">
        <pitch>
          <step>B</step>
          <alter>-1</alter>
          <octave>4</octave>
        </pitch>
        <duration>2520</duration>
        <type>16th</type>
        <accidental>flat</accidental>
        <stem>down</stem>
        <beam number="1">end</beam>
        <beam number="2">end</beam>
      </note>
    </measure>
    <!--======================== Measure 151 =========================-->
    <measure number="151">
      <note default-x="82.39" default-y="-25">
        <pitch>
          <step>A</step>
          <octave>4</octave>
        </pitch>
        <duration>2520</duration>
        <type>16th</type>
        <stem>up</stem>
        <beam number="1">begin</beam>
        <beam number="2">begin</beam>
      </note>
      <note default-x="203.94" default-y="-20">
        <pitch>
          <step>B</step>
          <alter>-1</alter>
          <octave>4</octave>
        </pitch>
        <duration>2520</duration>
        <type>16th</type>
        <accidental>flat</accidental>
        <stem>up</stem>
        <beam number="1">continue</beam>
        <beam number="2">continue</beam>
      </note>
      <note default-x="325.5" default-y="-25">
        <pitch>
          <step>A</step>
          <octave>4</octave>
        </pitch>
        <duration>2520</duration>
        <type>16th</type>
        <stem>up</stem>
        <beam number="1">continue</beam>
        <beam number="2">continue</beam>
      </note>
      <note default-x="447.05" default-y="-30">
        <pitch>
          <step>G</step>
          <alter>1</alter>
          <octave>4</octave>
        </pitch>
        <duration>2520</duration>
        <type>16th</type>
        <accidental>sharp</accidental>
        <stem>up</stem>
        <beam number="1">end</beam>
        <beam number="2">end</beam>
      </note>
      <note default-x="568.61" default-y="-25">
        <pitch>
          <step>A</step>
          <octave>4</octave>
        </pitch>
        <duration>2520</duration>
        <type>16th</type>
        <stem>up</stem>
        <beam number="1">begin</beam>
        <beam number="2">begin</beam>
      </note>
      <note default-x="690.16" default-y="-30">
        <pitch>
          <step>G</step>
          <alter>0</alter>
          <octave>4</octave>
        </pitch>
        <duration>2520</duration>
        <type>16th</type>
        <accidental>natural</accidental>
        <stem>up</stem>
        <beam number="1">continue</beam>
        <beam number="2">continue</beam>
      </note>
      <note default-x="811.72" default-y="-35">
        <pitch>
          <step>F</step>
          <alter>0</alter>
          <octave>4</octave>
        </pitch>
        <duration>2520</duration>
        <type>16th</type>
        <accidental>natural</accidental>
        <stem>up</stem>
        <beam number="1">continue</beam>
        <beam number="2">continue</beam>
      </note>
      <note default-x="933.27" default-y="-40">
        <pitch>
          <step>E</step>
          <octave>4</octave>
        </pitch>
        <duration>2520</duration>
        <type>16th</type>
        <stem>up</stem>
        <beam number="1">end</beam>
        <beam number="2">end</beam>
      </note>
    </measure>
    <!--======================== Measure 152 =========================-->
    <measure number="152">
      <note default-x="82.39" default-y="-45">
        <pitch>
          <step>D</step>
          <octave>4</octave>
        </pitch>
        <duration>2520</duration>
        <type>16th</type>
        <stem>up</stem>
        <beam number="1">begin</beam>
        <beam number="2">begin</beam>
      </note>
      <note default-x="113.94" default-y="-40">
        <pitch>
          <step>E</step>
          <octave>4</octave>
        </pitch>
        <duration>2520</duration>
        <type>16th</type>
        <stem>up</stem>
        <beam number="1">continue</beam>
        <beam number="2">continue</beam>
      </note>
      <note default-x="145.49" default-y="-35">
        <pitch>
          <step>F</step>
          <alter>0</alter>
          <octave>4</octave>
        </pitch>
        <duration>2520</duration>
        <type>16th</type>
        <accidental>natural</accidental>
        <stem>up</stem>
        <beam number="1">continue</beam>
        <beam number="2">continue</beam>
      </note>
      <note default-x="178.57" default-y="-50">
        <pitch>
          <step>C</step>
          <alter>1</alter>
          <octave>4</octave>
        </pitch>
        <duration>2520</duration>
        <type>16th</type>
        <accidental>sharp</accidental>
        <stem>up</stem>
        <beam number="1">end</beam>
        <beam number="2">end</beam>
      </note>
      <note default-x="210.13" default-y="-40">
        <pitch>
          <step>E</step>
          <octave>4</octave>
        </pitch>
        <duration>2520</duration>
        <type>16th</type>
        <stem>up</stem>
        <beam number="1">begin</beam>
        <beam number="2">begin</beam>
      </note>
      <note default-x="241.68" default-y="-45">
        <pitch>
          <step>D</step>
          <octave>4</octave>
        </pitch>
        <duration>2520</duration>
        <type>16th</type>
        <stem>up</stem>
        <beam number="1">continue</beam>
        <beam number="2">continue</beam>
      </note>
      <note default-x="273.23" default-y="-50">
        <pitch>
          <step>C</step>
          <alter>0</alter>
          <octave>4</octave>
        </pitch>
        <duration>2520</duration>
        <type>16th</type>
        <accidental>natural</accidental>
        <stem>up</stem>
        <beam number="1">continue</beam>
        <beam number="2">continue</beam>
      </note>
      <note default-x="306" default-y="-55">
        <pitch>
          <step>B</step>
          <alter>-1</alter>
          <octave>3</octave>
        </pitch>
        <duration>2520</duration>
        <type>16th</type>
        <accidental>flat</accidental>
        <stem>up</stem>
        <beam number="1">end</beam>
        <beam number="2">end</beam>
      </note>
    </measure>
  </part>
</score-partwise>