<?xml version="1.0" encoding="utf-8"?>
<!DOCTYPE score-partwise  PUBLIC "-//Recordare//DTD MusicXML 3.1 Partwise//EN" "http://www.musicxml.org/dtds/partwise.dtd">
<score-partwise version="3.1">
  <movement-title>Chorale_26800.xml</movement-title>
  <identification>
    <creator type="composer">Music21</creator>
    <encoding>
      <encoding-date>2025-07-03</encoding-date>
      <software>music21 v.8.3.0</software>
      <software>Finale 2008 for Macintosh</software>
      <software>Dolet Light for Finale 2008</software>
    </encoding>
  </identification>
  <defaults>
    <scaling>
      <millimeters>7</millimeters>
      <tenths>40</tenths>
    </scaling>
  </defaults>
  <part-list>
    <score-part id="Pa46bc9ec45d11f14d1331a5f6c7b708d">
      <part-name />
    </score-part>
    <score-part id="Pc7ab01e57637cc00d8fec724afeac97a">
      <part-name />
    </score-part>
    <score-part id="Pf691bfded48e51e173d5fd9102a75fc6">
      <part-name />
    </score-part>
    <score-part id="P944f95f2520feb2ce149976ff4fa4ec3">
      <part-name />
    </score-part>
  </part-list>
  <!--=========================== Part 1 ===========================-->
  <part id="Pa46bc9ec45d11f14d1331a5f6c7b708d">
    <!--========================= Measure 9 ==========================-->
    <measure number="9" width="276">
      <attributes>
        <divisions>10080</divisions>
        <key>
          <fifths>1</fifths>
          <mode>major</mode>
        </key>
        <time symbol="common">
          <beats>4</beats>
          <beat-type>4</beat-type>
        </time>
      </attributes>
      <note default-x="13">
        <pitch>
          <step>G</step>
          <octave>4</octave>
        </pitch>
        <duration>10080</duration>
        <type>quarter</type>
        <stem default-y="5.5">up</stem>
      </note>
      <note default-x="74">
        <pitch>
          <step>G</step>
          <octave>4</octave>
        </pitch>
        <duration>10080</duration>
        <type>quarter</type>
        <stem default-y="5.5">up</stem>
      </note>
      <note default-x="131">
        <pitch>
          <step>A</step>
          <octave>4</octave>
        </pitch>
        <duration>10080</duration>
        <type>quarter</type>
        <stem default-y="10.5">up</stem>
      </note>
      <note default-x="200">
        <pitch>
          <step>A</step>
          <octave>4</octave>
        </pitch>
        <duration>10080</duration>
        <type>quarter</type>
        <stem default-y="10.5">up</stem>
      </note>
    </measure>
    <!--========================= Measure 10 =========================-->
    <measure number="10" width="298">
      <note default-x="10">
        <pitch>
          <step>B</step>
          <octave>4</octave>
        </pitch>
        <duration>10080</duration>
        <type>quarter</type>
        <stem default-y="-55">down</stem>
      </note>
      <note default-x="86">
        <pitch>
          <step>C</step>
          <octave>5</octave>
        </pitch>
        <duration>10080</duration>
        <type>quarter</type>
        <stem default-y="-50">down</stem>
      </note>
      <note default-x="161">
        <pitch>
          <step>D</step>
          <octave>5</octave>
        </pitch>
        <duration>5040</duration>
        <type>eighth</type>
        <stem default-y="-45">down</stem>
        <beam number="1">begin</beam>
      </note>
      <note default-x="195">
        <pitch>
          <step>C</step>
          <octave>5</octave>
        </pitch>
        <duration>5040</duration>
        <type>eighth</type>
        <stem default-y="-50">down</stem>
        <beam number="1">end</beam>
      </note>
      <note default-x="229">
        <pitch>
          <step>B</step>
          <octave>4</octave>
        </pitch>
        <duration>10080</duration>
        <type>quarter</type>
        <stem default-y="-55">down</stem>
      </note>
    </measure>
    <!--========================= Measure 11 =========================-->
    <measure number="11" width="205">
      <note default-x="12">
        <pitch>
          <step>A</step>
          <octave>4</octave>
        </pitch>
        <duration>20160</duration>
        <type>half</type>
        <stem default-y="10.5">up</stem>
      </note>
      <note default-x="154">
        <pitch>
          <step>G</step>
          <octave>4</octave>
        </pitch>
        <duration>10080</duration>
        <type>quarter</type>
        <stem default-y="5.5">up</stem>
        <notations>
          <fermata type="upright" />
        </notations>
      </note>
      <note print-object="no" print-spacing="yes">
        <rest />
        <duration>10080</duration>
        <type>quarter</type>
      </note>
      <barline location="right">
        <bar-style>light-heavy</bar-style>
      </barline>
    </measure>
  </part>
  <!--=========================== Part 2 ===========================-->
  <part id="Pc7ab01e57637cc00d8fec724afeac97a">
    <!--========================= Measure 9 ==========================-->
    <measure number="9" width="276">
      <attributes>
        <divisions>10080</divisions>
        <key>
          <fifths>1</fifths>
          <mode>major</mode>
        </key>
        <time symbol="common">
          <beats>4</beats>
          <beat-type>4</beat-type>
        </time>
      </attributes>
      <note default-x="13">
        <pitch>
          <step>B</step>
          <octave>3</octave>
        </pitch>
        <duration>10080</duration>
        <type>quarter</type>
        <stem default-y="-19.5">up</stem>
      </note>
      <note default-x="74">
        <pitch>
          <step>E</step>
          <octave>4</octave>
        </pitch>
        <duration>5040</duration>
        <type>eighth</type>
        <stem default-y="-5">up</stem>
        <beam number="1">begin</beam>
      </note>
      <note default-x="103">
        <pitch>
          <step>D</step>
          <octave>4</octave>
        </pitch>
        <duration>5040</duration>
        <type>eighth</type>
        <stem default-y="-10">up</stem>
        <beam number="1">end</beam>
      </note>
      <note default-x="131">
        <pitch>
          <step>E</step>
          <octave>4</octave>
        </pitch>
        <duration>5040</duration>
        <type>eighth</type>
        <stem default-y="-5">up</stem>
        <beam number="1">begin</beam>
      </note>
      <note default-x="159">
        <pitch>
          <step>F</step>
          <alter>1</alter>
          <octave>4</octave>
        </pitch>
        <duration>2520</duration>
        <type>16th</type>
        <stem default-y="1">up</stem>
        <beam number="1">continue</beam>
        <beam number="2">begin</beam>
      </note>
      <note default-x="180">
        <pitch>
          <step>G</step>
          <octave>4</octave>
        </pitch>
        <duration>2520</duration>
        <type>16th</type>
        <stem default-y="5">up</stem>
        <beam number="1">end</beam>
        <beam number="2">end</beam>
      </note>
      <note default-x="200">
        <pitch>
          <step>A</step>
          <octave>4</octave>
        </pitch>
        <duration>5040</duration>
        <type>eighth</type>
        <stem default-y="10">up</stem>
        <beam number="1">begin</beam>
      </note>
      <note default-x="229">
        <pitch>
          <step>F</step>
          <alter>1</alter>
          <octave>4</octave>
        </pitch>
        <duration>5040</duration>
        <type>eighth</type>
        <stem default-y="0">up</stem>
        <beam number="1">end</beam>
      </note>
    </measure>
    <!--========================= Measure 10 =========================-->
    <measure number="10" width="298">
      <note default-x="10">
        <pitch>
          <step>D</step>
          <octave>4</octave>
        </pitch>
        <duration>5040</duration>
        <type>eighth</type>
        <stem default-y="-10">up</stem>
        <beam number="1">begin</beam>
      </note>
      <note default-x="44">
        <pitch>
          <step>E</step>
          <octave>4</octave>
        </pitch>
        <duration>2520</duration>
        <type>16th</type>
        <stem default-y="-4">up</stem>
        <beam number="1">continue</beam>
        <beam number="2">begin</beam>
      </note>
      <note default-x="65">
        <pitch>
          <step>F</step>
          <alter>1</alter>
          <octave>4</octave>
        </pitch>
        <duration>2520</duration>
        <type>16th</type>
        <stem default-y="0">up</stem>
        <beam number="1">end</beam>
        <beam number="2">end</beam>
      </note>
      <note default-x="86">
        <pitch>
          <step>G</step>
          <octave>4</octave>
        </pitch>
        <duration>5040</duration>
        <type>eighth</type>
        <stem default-y="5">up</stem>
        <beam number="1">begin</beam>
      </note>
      <note default-x="120">
        <pitch>
          <step>F</step>
          <alter>1</alter>
          <octave>4</octave>
        </pitch>
        <duration>2520</duration>
        <type>16th</type>
        <stem default-y="-1">up</stem>
        <beam number="1">continue</beam>
        <beam number="2">begin</beam>
      </note>
      <note default-x="140">
        <pitch>
          <step>E</step>
          <octave>4</octave>
        </pitch>
        <duration>2520</duration>
        <type>16th</type>
        <stem default-y="-5">up</stem>
        <beam number="1">end</beam>
        <beam number="2">end</beam>
      </note>
      <note default-x="161">
        <pitch>
          <step>F</step>
          <alter>1</alter>
          <octave>4</octave>
        </pitch>
        <duration>5040</duration>
        <type>eighth</type>
        <stem default-y="0">up</stem>
      </note>
      <note default-x="195">
        <pitch>
          <step>A</step>
          <octave>4</octave>
        </pitch>
        <duration>10080</duration>
        <type>quarter</type>
        <stem default-y="10.5">up</stem>
      </note>
      <note default-x="263">
        <pitch>
          <step>G</step>
          <octave>4</octave>
        </pitch>
        <duration>5040</duration>
        <type>eighth</type>
        <stem default-y="6">up</stem>
      </note>
    </measure>
    <!--========================= Measure 11 =========================-->
    <measure number="11" width="205">
      <note default-x="12">
        <pitch>
          <step>G</step>
          <octave>4</octave>
        </pitch>
        <duration>10080</duration>
        <type>quarter</type>
        <stem default-y="6">up</stem>
      </note>
      <note default-x="72">
        <pitch>
          <step>F</step>
          <alter>1</alter>
          <octave>4</octave>
        </pitch>
        <duration>10080</duration>
        <type>quarter</type>
        <stem default-y="0">up</stem>
      </note>
      <note default-x="154">
        <pitch>
          <step>D</step>
          <octave>4</octave>
        </pitch>
        <duration>10080</duration>
        <type>quarter</type>
        <stem default-y="-9">up</stem>
      </note>
      <note print-object="no" print-spacing="yes">
        <rest />
        <duration>10080</duration>
        <type>quarter</type>
      </note>
      <barline location="right">
        <bar-style>light-heavy</bar-style>
      </barline>
    </measure>
  </part>
  <!--=========================== Part 3 ===========================-->
  <part id="Pf691bfded48e51e173d5fd9102a75fc6">
    <!--========================= Measure 9 ==========================-->
    <measure number="9" width="276">
      <attributes>
        <divisions>10080</divisions>
        <key>
          <fifths>1</fifths>
          <mode>major</mode>
        </key>
        <time symbol="common">
          <beats>4</beats>
          <beat-type>4</beat-type>
        </time>
      </attributes>
      <note default-x="13">
        <pitch>
          <step>G</step>
          <octave>3</octave>
        </pitch>
        <duration>5040</duration>
        <type>eighth</type>
        <stem default-y="-49">down</stem>
        <beam number="1">begin</beam>
      </note>
      <note default-x="46">
        <pitch>
          <step>F</step>
          <alter>1</alter>
          <octave>3</octave>
        </pitch>
        <duration>5040</duration>
        <type>eighth</type>
        <stem default-y="-45">down</stem>
        <beam number="1">continue</beam>
      </note>
      <note default-x="74">
        <pitch>
          <step>G</step>
          <octave>3</octave>
        </pitch>
        <duration>5040</duration>
        <type>eighth</type>
        <stem default-y="-42">down</stem>
        <beam number="1">continue</beam>
      </note>
      <note default-x="103">
        <pitch>
          <step>B</step>
          <octave>3</octave>
        </pitch>
        <duration>5040</duration>
        <type>eighth</type>
        <stem default-y="-38.5">down</stem>
        <beam number="1">end</beam>
      </note>
      <note default-x="131">
        <pitch>
          <step>C</step>
          <octave>4</octave>
        </pitch>
        <duration>10080</duration>
        <tie type="start" />
        <type>quarter</type>
        <stem default-y="-25">down</stem>
        <notations>
          <tied type="start" />
        </notations>
      </note>
      <note default-x="200">
        <pitch>
          <step>C</step>
          <octave>4</octave>
        </pitch>
        <duration>5040</duration>
        <tie type="stop" />
        <type>eighth</type>
        <stem default-y="-25">down</stem>
        <beam number="1">begin</beam>
        <notations>
          <tied type="stop" />
        </notations>
      </note>
      <note default-x="229">
        <pitch>
          <step>D</step>
          <octave>4</octave>
        </pitch>
        <duration>2520</duration>
        <type>16th</type>
        <stem default-y="-25">down</stem>
        <beam number="1">continue</beam>
        <beam number="2">begin</beam>
      </note>
      <note default-x="253">
        <pitch>
          <step>C</step>
          <octave>4</octave>
        </pitch>
        <duration>2520</duration>
        <type>16th</type>
        <stem default-y="-25">down</stem>
        <beam number="1">end</beam>
        <beam number="2">end</beam>
      </note>
    </measure>
    <!--========================= Measure 10 =========================-->
    <measure number="10" width="298">
      <note default-x="10">
        <pitch>
          <step>B</step>
          <octave>3</octave>
        </pitch>
        <duration>10080</duration>
        <tie type="start" />
        <type>quarter</type>
        <stem default-y="-30">down</stem>
        <notations>
          <tied type="start" />
        </notations>
      </note>
      <note default-x="86">
        <pitch>
          <step>B</step>
          <octave>3</octave>
        </pitch>
        <duration>5040</duration>
        <tie type="stop" />
        <type>eighth</type>
        <stem default-y="-30">down</stem>
        <beam number="1">begin</beam>
        <notations>
          <tied type="stop" />
        </notations>
      </note>
      <note default-x="120">
        <pitch>
          <step>A</step>
          <octave>3</octave>
        </pitch>
        <duration>2520</duration>
        <type>16th</type>
        <stem default-y="-36">down</stem>
        <beam number="1">continue</beam>
        <beam number="2">begin</beam>
      </note>
      <note default-x="140">
        <pitch>
          <step>G</step>
          <octave>3</octave>
        </pitch>
        <duration>2520</duration>
        <type>16th</type>
        <stem default-y="-39.5">down</stem>
        <beam number="1">end</beam>
        <beam number="2">end</beam>
      </note>
      <note default-x="161">
        <pitch>
          <step>A</step>
          <octave>3</octave>
        </pitch>
        <duration>5040</duration>
        <type>eighth</type>
        <stem default-y="-35">down</stem>
        <beam number="1">begin</beam>
      </note>
      <note default-x="195">
        <pitch>
          <step>F</step>
          <alter>1</alter>
          <octave>4</octave>
        </pitch>
        <duration>5040</duration>
        <type>eighth</type>
        <stem default-y="-25">down</stem>
        <beam number="1">end</beam>
      </note>
      <note default-x="229">
        <pitch>
          <step>D</step>
          <octave>4</octave>
        </pitch>
        <duration>5040</duration>
        <type>eighth</type>
        <stem default-y="-20">down</stem>
        <beam number="1">begin</beam>
      </note>
      <note default-x="263">
        <pitch>
          <step>E</step>
          <octave>4</octave>
        </pitch>
        <duration>5040</duration>
        <type>eighth</type>
        <stem default-y="-15">down</stem>
        <beam number="1">end</beam>
      </note>
    </measure>
    <!--========================= Measure 11 =========================-->
    <measure number="11" width="205">
      <note default-x="12">
        <pitch>
          <step>E</step>
          <octave>4</octave>
        </pitch>
        <duration>5040</duration>
        <type>eighth</type>
        <stem default-y="-15">down</stem>
        <beam number="1">begin</beam>
      </note>
      <note default-x="43">
        <pitch>
          <step>C</step>
          <octave>4</octave>
        </pitch>
        <duration>5040</duration>
        <type>eighth</type>
        <stem default-y="-25">down</stem>
        <beam number="1">end</beam>
      </note>
      <note default-x="72">
        <pitch>
          <step>A</step>
          <octave>3</octave>
        </pitch>
        <duration>5040</duration>
        <type>eighth</type>
        <stem default-y="-35">down</stem>
        <beam number="1">begin</beam>
      </note>
      <note default-x="96">
        <pitch>
          <step>D</step>
          <octave>4</octave>
        </pitch>
        <duration>2520</duration>
        <type>16th</type>
        <stem default-y="-30">down</stem>
        <beam number="1">continue</beam>
        <beam number="2">begin</beam>
      </note>
      <note default-x="121">
        <pitch>
          <step>C</step>
          <octave>4</octave>
        </pitch>
        <duration>2520</duration>
        <type>16th</type>
        <stem default-y="-25">down</stem>
        <beam number="1">end</beam>
        <beam number="2">end</beam>
      </note>
      <note default-x="154">
        <pitch>
          <step>B</step>
          <octave>3</octave>
        </pitch>
        <duration>10080</duration>
        <type>quarter</type>
        <stem default-y="-30">down</stem>
      </note>
      <note print-object="no" print-spacing="yes">
        <rest />
        <duration>10080</duration>
        <type>quarter</type>
      </note>
      <barline location="right">
        <bar-style>light-heavy</bar-style>
      </barline>
    </measure>
  </part>
  <!--=========================== Part 4 ===========================-->
  <part id="P944f95f2520feb2ce149976ff4fa4ec3">
    <!--========================= Measure 9 ==========================-->
    <measure number="9" width="276">
      <attributes>
        <divisions>10080</divisions>
        <key>
          <fifths>1</fifths>
          <mode>major</mode>
        </key>
        <time symbol="common">
          <beats>4</beats>
          <beat-type>4</beat-type>
        </time>
      </attributes>
      <note default-x="13">
        <pitch>
          <step>E</step>
          <octave>3</octave>
        </pitch>
        <duration>5040</duration>
        <type>eighth</type>
        <stem default-y="20">up</stem>
        <beam number="1">begin</beam>
      </note>
      <note default-x="46">
        <pitch>
          <step>D</step>
          <alter>0</alter>
          <octave>3</octave>
        </pitch>
        <duration>5040</duration>
        <type>eighth</type>
        <accidental>natural</accidental>
        <stem default-y="16.5">up</stem>
        <beam number="1">continue</beam>
      </note>
      <note default-x="74">
        <pitch>
          <step>C</step>
          <octave>3</octave>
        </pitch>
        <duration>5040</duration>
        <type>eighth</type>
        <stem default-y="13.5">up</stem>
        <beam number="1">continue</beam>
      </note>
      <note default-x="103">
        <pitch>
          <step>B</step>
          <octave>2</octave>
        </pitch>
        <duration>5040</duration>
        <type>eighth</type>
        <stem default-y="10">up</stem>
        <beam number="1">end</beam>
      </note>
      <note default-x="131">
        <pitch>
          <step>A</step>
          <octave>2</octave>
        </pitch>
        <duration>5040</duration>
        <type>eighth</type>
        <stem default-y="0">up</stem>
        <beam number="1">begin</beam>
      </note>
      <note default-x="159">
        <pitch>
          <step>G</step>
          <octave>2</octave>
        </pitch>
        <duration>5040</duration>
        <type>eighth</type>
        <stem default-y="-3">up</stem>
        <beam number="1">continue</beam>
      </note>
      <note default-x="200">
        <pitch>
          <step>F</step>
          <alter>1</alter>
          <octave>2</octave>
        </pitch>
        <duration>5040</duration>
        <type>eighth</type>
        <stem default-y="-7">up</stem>
        <beam number="1">continue</beam>
      </note>
      <note default-x="229">
        <pitch>
          <step>D</step>
          <octave>2</octave>
        </pitch>
        <duration>5040</duration>
        <type>eighth</type>
        <stem default-y="-10">up</stem>
        <beam number="1">end</beam>
      </note>
    </measure>
    <!--========================= Measure 10 =========================-->
    <measure number="10" width="298">
      <note default-x="10">
        <pitch>
          <step>G</step>
          <octave>2</octave>
        </pitch>
        <duration>5040</duration>
        <type>eighth</type>
        <stem default-y="20">up</stem>
        <beam number="1">begin</beam>
      </note>
      <note default-x="44">
        <pitch>
          <step>G</step>
          <octave>3</octave>
        </pitch>
        <duration>5040</duration>
        <type>eighth</type>
        <stem default-y="30">up</stem>
        <beam number="1">end</beam>
      </note>
      <note default-x="86">
        <pitch>
          <step>E</step>
          <octave>3</octave>
        </pitch>
        <duration>5040</duration>
        <type>eighth</type>
        <stem default-y="-50">down</stem>
        <beam number="1">begin</beam>
      </note>
      <note default-x="120">
        <pitch>
          <step>A</step>
          <octave>3</octave>
        </pitch>
        <duration>5040</duration>
        <type>eighth</type>
        <stem default-y="-40">down</stem>
        <beam number="1">end</beam>
      </note>
      <note default-x="161">
        <pitch>
          <step>F</step>
          <alter>1</alter>
          <octave>3</octave>
        </pitch>
        <duration>5040</duration>
        <type>eighth</type>
        <stem default-y="-45">down</stem>
        <beam number="1">begin</beam>
      </note>
      <note default-x="195">
        <pitch>
          <step>D</step>
          <octave>3</octave>
        </pitch>
        <duration>5040</duration>
        <type>eighth</type>
        <stem default-y="-55">down</stem>
        <beam number="1">end</beam>
      </note>
      <note default-x="229">
        <pitch>
          <step>G</step>
          <octave>3</octave>
        </pitch>
        <duration>5040</duration>
        <type>eighth</type>
        <stem default-y="-40">down</stem>
        <beam number="1">begin</beam>
      </note>
      <note default-x="263">
        <pitch>
          <step>E</step>
          <octave>3</octave>
        </pitch>
        <duration>5040</duration>
        <type>eighth</type>
        <stem default-y="-50">down</stem>
        <beam number="1">end</beam>
      </note>
    </measure>
    <!--========================= Measure 11 =========================-->
    <measure number="11" width="205">
      <note default-x="12">
        <pitch>
          <step>C</step>
          <octave>3</octave>
        </pitch>
        <duration>5040</duration>
        <type>eighth</type>
        <stem default-y="10">up</stem>
        <beam number="1">begin</beam>
      </note>
      <note default-x="43">
        <pitch>
          <step>A</step>
          <octave>2</octave>
        </pitch>
        <duration>5040</duration>
        <type>eighth</type>
        <stem default-y="0">up</stem>
        <beam number="1">end</beam>
      </note>
      <note default-x="72">
        <pitch>
          <step>D</step>
          <octave>3</octave>
        </pitch>
        <duration>10080</duration>
        <type>quarter</type>
        <stem default-y="-55">down</stem>
      </note>
      <note default-x="154">
        <pitch>
          <step>G</step>
          <octave>2</octave>
        </pitch>
        <duration>10080</duration>
        <type>quarter</type>
        <stem default-y="-5">up</stem>
      </note>
      <note print-object="no" print-spacing="yes">
        <rest />
        <duration>10080</duration>
        <type>quarter</type>
      </note>
      <barline location="right">
        <bar-style>light-heavy</bar-style>
      </barline>
    </measure>
  </part>
</score-partwise>