<?xml version="1.0" encoding="utf-8"?>
<!DOCTYPE score-partwise  PUBLIC "-//Recordare//DTD MusicXML 3.1 Partwise//EN" "http://www.musicxml.org/dtds/partwise.dtd">
<score-partwise version="3.1">
  <movement-title>Chorale_38300.xml</movement-title>
  <identification>
    <creator type="composer">Music21</creator>
    <encoding>
      <encoding-date>2025-07-03</encoding-date>
      <software>music21 v.8.3.0</software>
      <software>Finale 2008 for Macintosh</software>
      <software>Dolet Light for Finale 2008</software>
    </encoding>
  </identification>
  <defaults>
    <scaling>
      <millimeters>7</millimeters>
      <tenths>40</tenths>
    </scaling>
  </defaults>
  <part-list>
    <score-part id="P0e255e390607ec1a8fcd0e8f7aa534a3">
      <part-name />
    </score-part>
    <score-part id="P68858d8b13079e371a9289e4f5ad231d">
      <part-name />
    </score-part>
    <score-part id="P793cc879c736ba5e41fe2a432bb2cc0f">
      <part-name />
    </score-part>
    <score-part id="P3041856f81bfaffb6e53da44e618ee5d">
      <part-name />
    </score-part>
  </part-list>
  <!--=========================== Part 1 ===========================-->
  <part id="P0e255e390607ec1a8fcd0e8f7aa534a3">
    <!--========================= Measure 27 =========================-->
    <measure number="27" width="255">
      <print new-system="yes" />
      <attributes>
        <divisions>10080</divisions>
        <key>
          <fifths>0</fifths>
          <mode>minor</mode>
        </key>
        <time symbol="common">
          <beats>4</beats>
          <beat-type>4</beat-type>
        </time>
      </attributes>
      <note default-x="52">
        <pitch>
          <step>A</step>
          <octave>4</octave>
        </pitch>
        <duration>10080</duration>
        <type>quarter</type>
        <stem default-y="10.5">up</stem>
      </note>
      <note default-x="97">
        <pitch>
          <step>B</step>
          <octave>4</octave>
        </pitch>
        <duration>10080</duration>
        <type>quarter</type>
        <stem default-y="-55">down</stem>
      </note>
      <note default-x="134">
        <pitch>
          <step>C</step>
          <octave>5</octave>
        </pitch>
        <duration>5040</duration>
        <type>eighth</type>
        <stem default-y="-50">down</stem>
        <beam number="1">begin</beam>
      </note>
      <note default-x="165">
        <pitch>
          <step>B</step>
          <octave>4</octave>
        </pitch>
        <duration>5040</duration>
        <type>eighth</type>
        <stem default-y="-55">down</stem>
        <beam number="1">end</beam>
      </note>
      <note default-x="188">
        <pitch>
          <step>A</step>
          <octave>4</octave>
        </pitch>
        <duration>10080</duration>
        <type>quarter</type>
        <stem default-y="10.5">up</stem>
      </note>
    </measure>
    <!--========================= Measure 28 =========================-->
    <measure number="28" width="160">
      <note default-x="10">
        <pitch>
          <step>G</step>
          <octave>4</octave>
        </pitch>
        <duration>20160</duration>
        <type>half</type>
        <stem default-y="6">up</stem>
        <notations>
          <fermata type="upright" />
        </notations>
      </note>
      <note print-object="no" print-spacing="yes">
        <rest />
        <duration>20160</duration>
        <type>half</type>
      </note>
    </measure>
  </part>
  <!--=========================== Part 2 ===========================-->
  <part id="P68858d8b13079e371a9289e4f5ad231d">
    <!--========================= Measure 27 =========================-->
    <measure number="27" width="255">
      <print new-system="yes" />
      <attributes>
        <divisions>10080</divisions>
        <key>
          <fifths>0</fifths>
          <mode>minor</mode>
        </key>
        <time symbol="common">
          <beats>4</beats>
          <beat-type>4</beat-type>
        </time>
      </attributes>
      <note default-x="52">
        <pitch>
          <step>C</step>
          <octave>4</octave>
        </pitch>
        <duration>10080</duration>
        <type>quarter</type>
        <stem default-y="-14.5">up</stem>
      </note>
      <note default-x="97">
        <pitch>
          <step>D</step>
          <octave>4</octave>
        </pitch>
        <duration>10080</duration>
        <type>quarter</type>
        <stem default-y="-10">up</stem>
      </note>
      <note default-x="134">
        <pitch>
          <step>E</step>
          <octave>4</octave>
        </pitch>
        <duration>5040</duration>
        <type>eighth</type>
        <stem default-y="-4.5">up</stem>
      </note>
      <note default-x="165">
        <pitch>
          <step>G</step>
          <octave>4</octave>
        </pitch>
        <duration>10080</duration>
        <type>quarter</type>
        <stem default-y="6">up</stem>
      </note>
      <note default-x="211">
        <pitch>
          <step>F</step>
          <alter>1</alter>
          <octave>4</octave>
        </pitch>
        <duration>5040</duration>
        <type>eighth</type>
        <accidental>sharp</accidental>
        <stem default-y="0">up</stem>
      </note>
    </measure>
    <!--========================= Measure 28 =========================-->
    <measure number="28" width="160">
      <note default-x="10">
        <pitch>
          <step>G</step>
          <octave>4</octave>
        </pitch>
        <duration>20160</duration>
        <type>half</type>
        <stem default-y="6">up</stem>
      </note>
      <note print-object="no" print-spacing="yes">
        <rest />
        <duration>20160</duration>
        <type>half</type>
      </note>
    </measure>
  </part>
  <!--=========================== Part 3 ===========================-->
  <part id="P793cc879c736ba5e41fe2a432bb2cc0f">
    <!--========================= Measure 27 =========================-->
    <measure number="27" width="255">
      <print new-system="yes">
        <staff-layout number="1">
          <staff-distance>67</staff-distance>
        </staff-layout>
      </print>
      <attributes>
        <divisions>10080</divisions>
        <key>
          <fifths>0</fifths>
          <mode>minor</mode>
        </key>
        <time symbol="common">
          <beats>4</beats>
          <beat-type>4</beat-type>
        </time>
        <staff-details print-object="yes" />
      </attributes>
      <note default-x="52">
        <pitch>
          <step>A</step>
          <octave>3</octave>
        </pitch>
        <duration>5040</duration>
        <type>eighth</type>
        <stem default-y="10">up</stem>
        <beam number="1">begin</beam>
      </note>
      <note default-x="75">
        <pitch>
          <step>G</step>
          <octave>3</octave>
        </pitch>
        <duration>5040</duration>
        <type>eighth</type>
        <stem default-y="5">up</stem>
        <beam number="1">end</beam>
      </note>
      <note default-x="97">
        <pitch>
          <step>F</step>
          <octave>3</octave>
        </pitch>
        <duration>10080</duration>
        <type>quarter</type>
        <stem default-y="0.5">up</stem>
      </note>
      <note default-x="134">
        <pitch>
          <step>G</step>
          <octave>3</octave>
        </pitch>
        <duration>5040</duration>
        <type>eighth</type>
        <stem default-y="-65">down</stem>
        <beam number="1">begin</beam>
      </note>
      <note default-x="165">
        <pitch>
          <step>E</step>
          <octave>4</octave>
        </pitch>
        <duration>5040</duration>
        <type>eighth</type>
        <stem default-y="-55">down</stem>
        <beam number="1">end</beam>
      </note>
      <note default-x="188">
        <pitch>
          <step>A</step>
          <octave>3</octave>
        </pitch>
        <duration>5040</duration>
        <type>eighth</type>
        <stem default-y="-60">down</stem>
        <beam number="1">begin</beam>
      </note>
      <note default-x="211">
        <pitch>
          <step>D</step>
          <octave>4</octave>
        </pitch>
        <duration>2520</duration>
        <type>16th</type>
        <stem default-y="-55">down</stem>
        <beam number="1">continue</beam>
        <beam number="2">begin</beam>
      </note>
      <note default-x="234">
        <pitch>
          <step>C</step>
          <octave>4</octave>
        </pitch>
        <duration>2520</duration>
        <type>16th</type>
        <stem default-y="-50">down</stem>
        <beam number="1">end</beam>
        <beam number="2">end</beam>
      </note>
    </measure>
    <!--========================= Measure 28 =========================-->
    <measure number="28" width="160">
      <note default-x="10">
        <pitch>
          <step>B</step>
          <octave>3</octave>
        </pitch>
        <duration>20160</duration>
        <type>half</type>
        <stem default-y="-55.5">down</stem>
      </note>
      <note print-object="no" print-spacing="yes">
        <rest />
        <duration>20160</duration>
        <type>half</type>
      </note>
    </measure>
  </part>
  <!--=========================== Part 4 ===========================-->
  <part id="P3041856f81bfaffb6e53da44e618ee5d">
    <!--========================= Measure 27 =========================-->
    <measure number="27" width="255">
      <print new-system="yes">
        <staff-layout number="1">
          <staff-distance>62</staff-distance>
        </staff-layout>
      </print>
      <attributes>
        <divisions>10080</divisions>
        <key>
          <fifths>0</fifths>
          <mode>minor</mode>
        </key>
        <time symbol="common">
          <beats>4</beats>
          <beat-type>4</beat-type>
        </time>
        <staff-details print-object="yes" />
      </attributes>
      <note default-x="52">
        <pitch>
          <step>F</step>
          <octave>3</octave>
        </pitch>
        <duration>5040</duration>
        <type>eighth</type>
        <stem default-y="-45">down</stem>
        <beam number="1">begin</beam>
      </note>
      <note default-x="75">
        <pitch>
          <step>E</step>
          <octave>3</octave>
        </pitch>
        <duration>5040</duration>
        <type>eighth</type>
        <stem default-y="-50">down</stem>
        <beam number="1">end</beam>
      </note>
      <note default-x="97">
        <pitch>
          <step>D</step>
          <octave>3</octave>
        </pitch>
        <duration>10080</duration>
        <type>quarter</type>
        <stem default-y="-55">down</stem>
      </note>
      <note default-x="134">
        <pitch>
          <step>C</step>
          <octave>3</octave>
        </pitch>
        <duration>10080</duration>
        <type>quarter</type>
        <stem default-y="10.5">up</stem>
      </note>
      <note default-x="188">
        <pitch>
          <step>D</step>
          <octave>3</octave>
        </pitch>
        <duration>10080</duration>
        <type>quarter</type>
        <stem default-y="-55">down</stem>
      </note>
    </measure>
    <!--========================= Measure 28 =========================-->
    <measure number="28" width="160">
      <note default-x="10">
        <pitch>
          <step>E</step>
          <octave>3</octave>
        </pitch>
        <duration>20160</duration>
        <type>half</type>
        <stem default-y="-50">down</stem>
      </note>
      <note print-object="no" print-spacing="yes">
        <rest />
        <duration>20160</duration>
        <type>half</type>
      </note>
    </measure>
  </part>
</score-partwise>